sinomaps/__init__.py
sinomaps/main.py
sinomaps-1.0.1.dist-info/DESCRIPTION.rst
sinomaps-1.0.1.dist-info/METADATA
sinomaps-1.0.1.dist-info/RECORD
sinomaps-1.0.1.dist-info/WHEEL
sinomaps-1.0.1.dist-info/metadata.json
sinomaps-1.0.1.dist-info/top_level.txt
