Metadata-Version: 2.0
Name: sinomaps
Version: 1.0.1
Summary: high school IT textbook resource, sinomaps version, 2018.
Home-page: https://www.sinomaps.com
Author: slobber
Author-email: me@nandi.wang
License: BSD
Keywords: teaching resource,high school
Platform: UNKNOWN
Requires-Dist: itchat
Requires-Dist: matplotlib
Requires-Dist: numpy
Requires-Dist: pandas (>=0.22.0)
Requires-Dist: requests (>=2.18.0)
